<annotation>
	<folder>21-11</folder>
	<filename>DSC06833.JPG</filename>
	<path>G:\Huerta\21-11\DSC06833.JPG</path>
	<source>
		<database>Unknown</database>
	</source>
	<size>
		<width>800</width>
		<height>600</height>
		<depth>3</depth>
	</size>
	<segmented>0</segmented>
	<object>
		<name>Espinaca</name>
		<pose>Unspecified</pose>
		<truncated>0</truncated>
		<difficult>0</difficult>
		<bndbox>
			<xmin>3</xmin>
			<ymin>4</ymin>
			<xmax>264</xmax>
			<ymax>168</ymax>
		</bndbox>
	</object>
	<object>
		<name>Espinaca</name>
		<pose>Unspecified</pose>
		<truncated>0</truncated>
		<difficult>0</difficult>
		<bndbox>
			<xmin>286</xmin>
			<ymin>27</ymin>
			<xmax>454</xmax>
			<ymax>143</ymax>
		</bndbox>
	</object>
	<object>
		<name>Espinaca</name>
		<pose>Unspecified</pose>
		<truncated>0</truncated>
		<difficult>0</difficult>
		<bndbox>
			<xmin>557</xmin>
			<ymin>20</ymin>
			<xmax>682</xmax>
			<ymax>155</ymax>
		</bndbox>
	</object>
	<object>
		<name>Espinaca</name>
		<pose>Unspecified</pose>
		<truncated>0</truncated>
		<difficult>0</difficult>
		<bndbox>
			<xmin>551</xmin>
			<ymin>250</ymin>
			<xmax>675</xmax>
			<ymax>331</ymax>
		</bndbox>
	</object>
	<object>
		<name>Espinaca</name>
		<pose>Unspecified</pose>
		<truncated>0</truncated>
		<difficult>0</difficult>
		<bndbox>
			<xmin>267</xmin>
			<ymin>127</ymin>
			<xmax>545</xmax>
			<ymax>333</ymax>
		</bndbox>
	</object>
	<object>
		<name>Espinaca</name>
		<pose>Unspecified</pose>
		<truncated>0</truncated>
		<difficult>0</difficult>
		<bndbox>
			<xmin>60</xmin>
			<ymin>180</ymin>
			<xmax>237</xmax>
			<ymax>328</ymax>
		</bndbox>
	</object>
</annotation>
