<annotation>
	<folder>21-11</folder>
	<filename>DSC06564.JPG</filename>
	<path>G:\Huerta\21-11\DSC06564.JPG</path>
	<source>
		<database>Unknown</database>
	</source>
	<size>
		<width>800</width>
		<height>600</height>
		<depth>3</depth>
	</size>
	<segmented>0</segmented>
	<object>
		<name>Espinaca</name>
		<pose>Unspecified</pose>
		<truncated>0</truncated>
		<difficult>0</difficult>
		<bndbox>
			<xmin>121</xmin>
			<ymin>150</ymin>
			<xmax>316</xmax>
			<ymax>387</ymax>
		</bndbox>
	</object>
	<object>
		<name>Espinaca</name>
		<pose>Unspecified</pose>
		<truncated>0</truncated>
		<difficult>0</difficult>
		<bndbox>
			<xmin>204</xmin>
			<ymin>11</ymin>
			<xmax>329</xmax>
			<ymax>117</ymax>
		</bndbox>
	</object>
	<object>
		<name>Espinaca</name>
		<pose>Unspecified</pose>
		<truncated>0</truncated>
		<difficult>0</difficult>
		<bndbox>
			<xmin>459</xmin>
			<ymin>17</ymin>
			<xmax>623</xmax>
			<ymax>78</ymax>
		</bndbox>
	</object>
	<object>
		<name>Espinaca</name>
		<pose>Unspecified</pose>
		<truncated>0</truncated>
		<difficult>0</difficult>
		<bndbox>
			<xmin>618</xmin>
			<ymin>109</ymin>
			<xmax>648</xmax>
			<ymax>184</ymax>
		</bndbox>
	</object>
	<object>
		<name>Espinaca</name>
		<pose>Unspecified</pose>
		<truncated>0</truncated>
		<difficult>0</difficult>
		<bndbox>
			<xmin>568</xmin>
			<ymin>177</ymin>
			<xmax>608</xmax>
			<ymax>229</ymax>
		</bndbox>
	</object>
	<object>
		<name>Espinaca</name>
		<pose>Unspecified</pose>
		<truncated>0</truncated>
		<difficult>0</difficult>
		<bndbox>
			<xmin>521</xmin>
			<ymin>240</ymin>
			<xmax>559</xmax>
			<ymax>304</ymax>
		</bndbox>
	</object>
	<object>
		<name>Espinaca</name>
		<pose>Unspecified</pose>
		<truncated>0</truncated>
		<difficult>0</difficult>
		<bndbox>
			<xmin>320</xmin>
			<ymin>272</ymin>
			<xmax>405</xmax>
			<ymax>360</ymax>
		</bndbox>
	</object>
	<object>
		<name>Espinaca</name>
		<pose>Unspecified</pose>
		<truncated>0</truncated>
		<difficult>0</difficult>
		<bndbox>
			<xmin>706</xmin>
			<ymin>6</ymin>
			<xmax>793</xmax>
			<ymax>117</ymax>
		</bndbox>
	</object>
	<object>
		<name>Espinaca</name>
		<pose>Unspecified</pose>
		<truncated>0</truncated>
		<difficult>0</difficult>
		<bndbox>
			<xmin>77</xmin>
			<ymin>340</ymin>
			<xmax>115</xmax>
			<ymax>391</ymax>
		</bndbox>
	</object>
</annotation>
